flask_crud_routes/__init__.py
flask_crud_routes/router.py
flask_crud_routes-0.0.2.dist-info/LICENSE
flask_crud_routes-0.0.2.dist-info/METADATA
flask_crud_routes-0.0.2.dist-info/WHEEL
flask_crud_routes-0.0.2.dist-info/top_level.txt
flask_crud_routes-0.0.2.dist-info/RECORD
